pyomo_cpsat/__init__.py
pyomo_cpsat/cpsat.py
pyomo_cpsat-2026.1.29.dist-info/licenses/LICENSE
pyomo_cpsat-2026.1.29.dist-info/WHEEL
pyomo_cpsat-2026.1.29.dist-info/METADATA
pyomo_cpsat-2026.1.29.dist-info/RECORD
