Metadata-Version: 2.4
Name: pyomo-cpsat
Version: 2026.1.29
Summary: Pyomo interface to CP-SAT
Author-email: Nelson Uhan <nelson@uhan.me>
License-File: LICENSE
Requires-Dist: pyomo >= 6.9.2
Requires-Dist: ortools >= 9.12
Project-URL: Home, https://github.com/nelsonuhan/pyomo-cpsat
